dinamicarslib/__init__.py
dinamicarslib/dataset.py
dinamicarslib/earth_engine.py
dinamicarslib/image_processing.py
dinamicarslib/utils.py
dinamicarslib/vector.py
dinamicarslib-0.0.3.dist-info/licenses/LICENSE
dinamicarslib-0.0.3.dist-info/METADATA
dinamicarslib-0.0.3.dist-info/WHEEL
dinamicarslib-0.0.3.dist-info/top_level.txt
dinamicarslib-0.0.3.dist-info/RECORD
