Metadata-Version: 2.4
Name: dinamicarslib
Version: 0.0.3
Summary: python package with remote sensing function to work integrated with DinamicaEGO
Author-email: Fabrício Fernandes <fabricio.fernandes@inteligenciaterritorial.org>
License-Expression: GPL-3.0-or-later
Project-URL: Homepage, https://github.com/pypa/sampleproject
Project-URL: Issues, https://github.com/pypa/sampleproject/issues
Keywords: Remote Sensing,DinamicaEGO,GIS,Machine Learning
Classifier: Programming Language :: Python :: 3
Classifier: Operating System :: OS Independent
Requires-Python: >=3.12
License-File: LICENSE
Requires-Dist: pandas
Requires-Dist: geopandas
Requires-Dist: xarray
Requires-Dist: rioxarray
Requires-Dist: scikit-learn
Requires-Dist: pyarrow
Dynamic: license-file
